simpletransformers/__init__.py
simpletransformers/model.py
simpletransformers/classification/__init__.py
simpletransformers/classification/classification_model.py
simpletransformers/classification/classification_utils.py
simpletransformers/classification/multi_label_classification_model.py
simpletransformers/classification/multi_modal_classification_model.py
simpletransformers/classification/transformer_models/__init__.py
simpletransformers/classification/transformer_models/albert_model.py
simpletransformers/classification/transformer_models/bert_model.py
simpletransformers/classification/transformer_models/camembert_model.py
simpletransformers/classification/transformer_models/distilbert_model.py
simpletransformers/classification/transformer_models/electra_model.py
simpletransformers/classification/transformer_models/flaubert_model.py
simpletransformers/classification/transformer_models/layoutlm_model.py
simpletransformers/classification/transformer_models/longformer_model.py
simpletransformers/classification/transformer_models/mmbt_model.py
simpletransformers/classification/transformer_models/mobilebert_model.py
simpletransformers/classification/transformer_models/roberta_model.py
simpletransformers/classification/transformer_models/xlm_model.py
simpletransformers/classification/transformer_models/xlm_roberta_model.py
simpletransformers/classification/transformer_models/xlnet_model.py
simpletransformers/config/__init__.py
simpletransformers/config/global_args.py
simpletransformers/config/model_args.py
simpletransformers/config/utils.py
simpletransformers/conv_ai/__init__.py
simpletransformers/conv_ai/conv_ai_model.py
simpletransformers/conv_ai/conv_ai_utils.py
simpletransformers/custom_models/__init__.py
simpletransformers/custom_models/models.py
simpletransformers/experimental/__init__.py
simpletransformers/experimental/classification/__init__.py
simpletransformers/experimental/classification/classification_model.py
simpletransformers_le-0.0.1.dev7.dist-info/LICENSE
simpletransformers_le-0.0.1.dev7.dist-info/METADATA
simpletransformers_le-0.0.1.dev7.dist-info/WHEEL
simpletransformers_le-0.0.1.dev7.dist-info/top_level.txt
simpletransformers_le-0.0.1.dev7.dist-info/RECORD
